cdbx/__init__.py
cdbx/_cdb.cpython-310-aarch64-linux-gnu.so
cdbx-0.2.6.dist-info/METADATA
cdbx-0.2.6.dist-info/WHEEL
cdbx-0.2.6.dist-info/top_level.txt
cdbx-0.2.6.dist-info/RECORD
cdbx-0.2.6.dist-info/licenses/LICENSE
